easyclimate_backend/__init__.py
easyclimate_backend/version.py
easyclimate_backend/aerobulk/LICENSE
easyclimate_backend/aerobulk/README.md
easyclimate_backend/aerobulk/__init__.py
easyclimate_backend/aerobulk/flux.py
easyclimate_backend/aerobulk/mod_aerobulk_wrap_noskin.cpython-313-x86_64-linux-gnu.so
easyclimate_backend/aerobulk/mod_aerobulk_wrap_skin.cpython-313-x86_64-linux-gnu.so
easyclimate_backend/contrack/LICENSE
easyclimate_backend/contrack/README.rst
easyclimate_backend/contrack/__init__.py
easyclimate_backend/contrack/contrack.py
easyclimate_backend/heat_stress/LICENSE
easyclimate_backend/heat_stress/__init__.py
easyclimate_backend/heat_stress/human_index_mod.cpython-313-x86_64-linux-gnu.so
easyclimate_backend/heat_stress/human_index_mod_old.cpython-313-x86_64-linux-gnu.so
easyclimate_backend/mjoindices/LICENSE
easyclimate_backend/mjoindices/__init__.py
easyclimate_backend/mjoindices/_version.py
easyclimate_backend/mjoindices/empirical_orthogonal_functions.py
easyclimate_backend/mjoindices/evaluation_tools.py
easyclimate_backend/mjoindices/olr_handling.py
easyclimate_backend/mjoindices/principal_components.py
easyclimate_backend/mjoindices/tools.py
easyclimate_backend/mjoindices/omi/__init__.py
easyclimate_backend/mjoindices/omi/omi_calculator.py
easyclimate_backend/mjoindices/omi/postprocessing_original_kiladis2014.py
easyclimate_backend/mjoindices/omi/postprocessing_rotation_approach.py
easyclimate_backend/mjoindices/omi/quick_temporal_filter.py
easyclimate_backend/mjoindices/omi/wheeler_kiladis_mjo_filter.py
easyclimate_backend/mjoindices/omi/sign_reference/eof1/eof001.txt
easyclimate_backend/mjoindices/omi/sign_reference/eof2/eof001.txt
easyclimate_backend/ncl/__init__.py
easyclimate_backend/pyspharm/LICENSE.spherepack
easyclimate_backend/pyspharm/README.md
easyclimate_backend/pyspharm/__init__.py
easyclimate_backend/pyspharm/_spherepack.cpython-313-x86_64-linux-gnu.so
easyclimate_backend/pyspharm/create_docs.sh
easyclimate_backend-2026.1.0.dist-info/LICENSE
easyclimate_backend-2026.1.0.dist-info/METADATA
easyclimate_backend-2026.1.0.dist-info/WHEEL
easyclimate_backend-2026.1.0.dist-info/RECORD
easyclimate_backend-2026.1.0.dist-info/sboms/auditwheel.cdx.json
