Metadata-Version: 2.1
Name: easyclimate-backend
Version: 2026.1.0
Summary: The backend of easyclimate
Author: shenyulu
License: BSD 3-Clause License
Classifier: Programming Language :: Python
Classifier: Programming Language :: Python :: 3
Classifier: Programming Language :: Python :: 3.10
Classifier: Programming Language :: Python :: 3.11
Classifier: Programming Language :: Python :: 3.12
Classifier: Programming Language :: Python :: 3.13
Classifier: Programming Language :: Python :: 3 :: Only
Classifier: Topic :: Scientific/Engineering
Classifier: Operating System :: Microsoft :: Windows
Classifier: Operating System :: POSIX
Classifier: Operating System :: Unix
Project-URL: homepage, https://github.com/shenyulu/easyclimate-backend
Project-URL: documentation, https://github.com/shenyulu/easyclimate-backend
Project-URL: source, https://github.com/shenyulu/easyclimate-backend
Project-URL: download, https://pypi.org/project/easyclimate-backend/#files
Project-URL: tracker, https://github.com/shenyulu/easyclimate-backend/issues
Requires-Python: >=3.10
Requires-Dist: numpy>=1.24.3
Requires-Dist: intel-fortran-rt
Requires-Dist: dpcpp-cpp-rt
Requires-Dist: wrapt
